{
  "creator": "Yosys 0.48+5 (git sha1 7a362f1f7, clang++ 18.1.8 -fPIC -O3)",
  "modules": {
    "WaveFormGenerator": {
      "attributes": {
        "top": "00000000000000000000000000000001",
        "src": "generators/generated/verilog_clean/WaveFormGenerator.v:1.1-28.10"
      },
      "ports": {
        "clock": {
          "direction": "input",
          "bits": [ 2 ]
        },
        "reset": {
          "direction": "input",
          "bits": [ 3 ]
        },
        "io_randomWave": {
          "direction": "output",
          "bits": [ 4 ]
        },
        "io_clockWave": {
          "direction": "output",
          "bits": [ 5 ]
        }
      },
      "cells": {
        "$abc$209$auto$blifparse.cc:396:parse_blif$210": {
          "hide_name": 1,
          "type": "$_NOT_",
          "parameters": {
          },
          "attributes": {
          },
          "port_directions": {
            "A": "input",
            "Y": "output"
          },
          "connections": {
            "A": [ 6 ],
            "Y": [ 7 ]
          }
        },
        "$abc$209$auto$blifparse.cc:396:parse_blif$211": {
          "hide_name": 1,
          "type": "$_OR_",
          "parameters": {
          },
          "attributes": {
          },
          "port_directions": {
            "A": "input",
            "B": "input",
            "Y": "output"
          },
          "connections": {
            "A": [ 8 ],
            "B": [ 6 ],
            "Y": [ 9 ]
          }
        },
        "$abc$209$auto$blifparse.cc:396:parse_blif$212": {
          "hide_name": 1,
          "type": "$_ANDNOT_",
          "parameters": {
          },
          "attributes": {
          },
          "port_directions": {
            "A": "input",
            "B": "input",
            "Y": "output"
          },
          "connections": {
            "A": [ 10 ],
            "B": [ 9 ],
            "Y": [ 11 ]
          }
        },
        "$abc$209$auto$blifparse.cc:396:parse_blif$213": {
          "hide_name": 1,
          "type": "$_OR_",
          "parameters": {
          },
          "attributes": {
          },
          "port_directions": {
            "A": "input",
            "B": "input",
            "Y": "output"
          },
          "connections": {
            "A": [ 11 ],
            "B": [ 3 ],
            "Y": [ 12 ]
          }
        },
        "$abc$209$auto$blifparse.cc:396:parse_blif$214": {
          "hide_name": 1,
          "type": "$_ANDNOT_",
          "parameters": {
          },
          "attributes": {
          },
          "port_directions": {
            "A": "input",
            "B": "input",
            "Y": "output"
          },
          "connections": {
            "A": [ 6 ],
            "B": [ 10 ],
            "Y": [ 4 ]
          }
        },
        "$abc$209$auto$blifparse.cc:396:parse_blif$215": {
          "hide_name": 1,
          "type": "$_NOT_",
          "parameters": {
          },
          "attributes": {
          },
          "port_directions": {
            "A": "input",
            "Y": "output"
          },
          "connections": {
            "A": [ 5 ],
            "Y": [ 13 ]
          }
        },
        "$abc$209$auto$blifparse.cc:396:parse_blif$216": {
          "hide_name": 1,
          "type": "$_XOR_",
          "parameters": {
          },
          "attributes": {
          },
          "port_directions": {
            "A": "input",
            "B": "input",
            "Y": "output"
          },
          "connections": {
            "A": [ 8 ],
            "B": [ 6 ],
            "Y": [ 14 ]
          }
        },
        "$abc$209$auto$blifparse.cc:396:parse_blif$217": {
          "hide_name": 1,
          "type": "$_AND_",
          "parameters": {
          },
          "attributes": {
          },
          "port_directions": {
            "A": "input",
            "B": "input",
            "Y": "output"
          },
          "connections": {
            "A": [ 8 ],
            "B": [ 6 ],
            "Y": [ 15 ]
          }
        },
        "$abc$209$auto$blifparse.cc:396:parse_blif$218": {
          "hide_name": 1,
          "type": "$_XOR_",
          "parameters": {
          },
          "attributes": {
          },
          "port_directions": {
            "A": "input",
            "B": "input",
            "Y": "output"
          },
          "connections": {
            "A": [ 15 ],
            "B": [ 10 ],
            "Y": [ 16 ]
          }
        },
        "$auto$ff.cc:266:slice$146": {
          "hide_name": 1,
          "type": "$_SDFF_PP0_",
          "parameters": {
          },
          "attributes": {
            "src": "generators/generated/verilog_clean/WaveFormGenerator.v:14.2-22.6"
          },
          "port_directions": {
            "C": "input",
            "D": "input",
            "Q": "output",
            "R": "input"
          },
          "connections": {
            "C": [ 2 ],
            "D": [ 13 ],
            "Q": [ 5 ],
            "R": [ 3 ]
          }
        },
        "$auto$ff.cc:266:slice$147": {
          "hide_name": 1,
          "type": "$_SDFF_PP0_",
          "parameters": {
          },
          "attributes": {
            "src": "generators/generated/verilog_clean/WaveFormGenerator.v:14.2-22.6"
          },
          "port_directions": {
            "C": "input",
            "D": "input",
            "Q": "output",
            "R": "input"
          },
          "connections": {
            "C": [ 2 ],
            "D": [ 7 ],
            "Q": [ 6 ],
            "R": [ 12 ]
          }
        },
        "$auto$ff.cc:266:slice$148": {
          "hide_name": 1,
          "type": "$_SDFF_PP0_",
          "parameters": {
          },
          "attributes": {
            "src": "generators/generated/verilog_clean/WaveFormGenerator.v:14.2-22.6"
          },
          "port_directions": {
            "C": "input",
            "D": "input",
            "Q": "output",
            "R": "input"
          },
          "connections": {
            "C": [ 2 ],
            "D": [ 14 ],
            "Q": [ 8 ],
            "R": [ 12 ]
          }
        },
        "$auto$ff.cc:266:slice$149": {
          "hide_name": 1,
          "type": "$_SDFF_PP0_",
          "parameters": {
          },
          "attributes": {
            "src": "generators/generated/verilog_clean/WaveFormGenerator.v:14.2-22.6"
          },
          "port_directions": {
            "C": "input",
            "D": "input",
            "Q": "output",
            "R": "input"
          },
          "connections": {
            "C": [ 2 ],
            "D": [ 16 ],
            "Q": [ 10 ],
            "R": [ 12 ]
          }
        }
      },
      "netnames": {
        "$abc$209$auto$opt_dff.cc:253:combine_resets$18": {
          "hide_name": 1,
          "bits": [ 12 ],
          "attributes": {
          }
        },
        "$abc$209$new_n13": {
          "hide_name": 1,
          "bits": [ 9 ],
          "attributes": {
          }
        },
        "$abc$209$new_n14": {
          "hide_name": 1,
          "bits": [ 11 ],
          "attributes": {
          }
        },
        "$abc$209$new_n19": {
          "hide_name": 1,
          "bits": [ 15 ],
          "attributes": {
          }
        },
        "$abc$209$not$generators/generated/verilog_clean/WaveFormGenerator.v:21$5_Y": {
          "hide_name": 1,
          "bits": [ 13 ],
          "attributes": {
            "src": "generators/generated/verilog_clean/WaveFormGenerator.v:21.19-21.31"
          }
        },
        "$auto$alumacc.cc:485:replace_alu$20.X": {
          "hide_name": 1,
          "bits": [ 7, 8, 10 ],
          "attributes": {
            "force_downto": "00000000000000000000000000000001",
            "src": "generators/generated/verilog_clean/WaveFormGenerator.v:20.49-20.67|/home/jglossner/Programs/oss-cad-suite/lib/../share/yosys/techmap.v:270.23-270.24"
          }
        },
        "$auto$alumacc.cc:485:replace_alu$20.Y": {
          "hide_name": 1,
          "bits": [ 7, 14, 16 ],
          "attributes": {
            "force_downto": "00000000000000000000000000000001",
            "src": "generators/generated/verilog_clean/WaveFormGenerator.v:20.49-20.67|/home/jglossner/Programs/oss-cad-suite/lib/../share/yosys/techmap.v:270.26-270.27"
          }
        },
        "_GEN": {
          "hide_name": 0,
          "bits": [ "0", "1", "0", "1", "0", "0", "0", "0" ],
          "attributes": {
            "src": "generators/generated/verilog_clean/WaveFormGenerator.v:11.13-11.17"
          }
        },
        "clock": {
          "hide_name": 0,
          "bits": [ 2 ],
          "attributes": {
            "src": "generators/generated/verilog_clean/WaveFormGenerator.v:7.8-7.13"
          }
        },
        "clockToggle": {
          "hide_name": 0,
          "bits": [ 5 ],
          "attributes": {
            "src": "generators/generated/verilog_clean/WaveFormGenerator.v:13.6-13.17"
          }
        },
        "io_clockWave": {
          "hide_name": 0,
          "bits": [ 5 ],
          "attributes": {
            "src": "generators/generated/verilog_clean/WaveFormGenerator.v:10.14-10.26"
          }
        },
        "io_randomWave": {
          "hide_name": 0,
          "bits": [ 4 ],
          "attributes": {
            "src": "generators/generated/verilog_clean/WaveFormGenerator.v:9.14-9.27"
          }
        },
        "randomIndex": {
          "hide_name": 0,
          "bits": [ 6, 8, 10 ],
          "attributes": {
            "src": "generators/generated/verilog_clean/WaveFormGenerator.v:12.12-12.23"
          }
        },
        "reset": {
          "hide_name": 0,
          "bits": [ 3 ],
          "attributes": {
            "src": "generators/generated/verilog_clean/WaveFormGenerator.v:8.8-8.13"
          }
        }
      }
    }
  }
}
